tronpy/__init__.py
tronpy/abi.py
tronpy/async_contract.py
tronpy/async_tron.py
tronpy/contract.py
tronpy/defaults.py
tronpy/exceptions.py
tronpy/tron.py
tronpy/version.py
tronpy/hdwallet/__init__.py
tronpy/hdwallet/_utils.py
tronpy/hdwallet/deterministic.py
tronpy/keys/__init__.py
tronpy/proto/__init__.py
tronpy/proto/transaction.py
tronpy/proto/tron.proto
tronpy/proto/tron_pb2.py
tronpy/proto/tron_pb2.pyi
tronpy/providers/__init__.py
tronpy/providers/async_http.py
tronpy/providers/http.py
tronpy-0.6.0.dist-info/METADATA
tronpy-0.6.0.dist-info/WHEEL
tronpy-0.6.0.dist-info/licenses/LICENSE
tronpy-0.6.0.dist-info/RECORD
